package/__init__.py
package/playf.py
krestnullbests-1.5.dist-info/LICENSE
krestnullbests-1.5.dist-info/METADATA
krestnullbests-1.5.dist-info/WHEEL
krestnullbests-1.5.dist-info/top_level.txt
krestnullbests-1.5.dist-info/RECORD
