Metadata-Version: 2.1
Name: krestnullbests
Version: 1.5
Summary: BEST
Home-page: https://pypi.org/krestnullbests
Author: Python_Palma
Author-email: xaker_1515@mail.ru
Project-URL: Documentation, https://youtube.com/
Keywords: Snake,python,Palma
Classifier: Programming Language :: Python :: 3.11
Classifier: License :: OSI Approved :: MIT License
Classifier: Operating System :: OS Independent
Requires-Python: >=3.5
License-File: LICENSE
Requires-Dist: requests >=2.25.1
Requires-Dist: art
